doplaydo/dodata_core/__init__.py
doplaydo/dodata_core/models.py
doplaydo/dodata_core/py.typed
dodata_core-0.5.1.dist-info/LICENSE
dodata_core-0.5.1.dist-info/METADATA
dodata_core-0.5.1.dist-info/WHEEL
dodata_core-0.5.1.dist-info/top_level.txt
dodata_core-0.5.1.dist-info/RECORD
