Metadata-Version: 2.1
Name: dodata_core
Version: 0.5.1
Summary: Core for DoData
Author-email: DoPlayDo <contact@doplaydo.com>
License: The MIT License (MIT)
Classifier: Programming Language :: Python :: 3.11
Classifier: Operating System :: OS Independent
Requires-Python: >=3.11
License-File: LICENSE
Requires-Dist: psycopg2-binary
Requires-Dist: pydantic <3,>=2
Requires-Dist: pydantic-settings
Requires-Dist: sqlmodel >=0.0.14
Provides-Extra: dev
Requires-Dist: ruff ; extra == 'dev'
Requires-Dist: mypy ; extra == 'dev'
Requires-Dist: pre-commit ; extra == 'dev'
Requires-Dist: pytest ; extra == 'dev'
Requires-Dist: towncrier ; extra == 'dev'
Requires-Dist: tbump ; extra == 'dev'
Requires-Dist: pytest-regressions ; extra == 'dev'
Requires-Dist: pytest-cov ; extra == 'dev'
Provides-Extra: maintainer
Requires-Dist: pylsp-mypy ; extra == 'maintainer'
Requires-Dist: python-lsp-server[all] ; extra == 'maintainer'
Requires-Dist: python-lsp-ruff ; extra == 'maintainer'
